LICENSE.txt
MANIFEST.in
README.rst
setup.cfg
setup.py
setup_util.py
versioneer.py
msmtools/__init__.py
msmtools/_version.py
msmtools.egg-info/PKG-INFO
msmtools.egg-info/SOURCES.txt
msmtools.egg-info/dependency_links.txt
msmtools.egg-info/not-zip-safe
msmtools.egg-info/requires.txt
msmtools.egg-info/top_level.txt
msmtools/analysis/__init__.py
msmtools/analysis/api.py
msmtools/analysis/dense/__init__.py
msmtools/analysis/dense/assessment.py
msmtools/analysis/dense/assessment_test.py
msmtools/analysis/dense/committor.py
msmtools/analysis/dense/committor_test.py
msmtools/analysis/dense/correlations.py
msmtools/analysis/dense/correlations_test.py
msmtools/analysis/dense/decomposition.py
msmtools/analysis/dense/decomposition_test.py
msmtools/analysis/dense/expectations.py
msmtools/analysis/dense/expectations_test.py
msmtools/analysis/dense/fingerprints.py
msmtools/analysis/dense/fingerprints_test.py
msmtools/analysis/dense/hitting_probability.py
msmtools/analysis/dense/hitting_probability_test.py
msmtools/analysis/dense/mean_first_passage_time.py
msmtools/analysis/dense/mean_first_passage_time_test.py
msmtools/analysis/dense/pcca.py
msmtools/analysis/dense/pcca_test.py
msmtools/analysis/dense/sensitivity.py
msmtools/analysis/dense/sensitivity_test.py
msmtools/analysis/dense/stationary_vector.py
msmtools/analysis/dense/stationary_vector_test.py
msmtools/analysis/sparse/__init__.py
msmtools/analysis/sparse/assessment.py
msmtools/analysis/sparse/assessment_test.py
msmtools/analysis/sparse/committor.py
msmtools/analysis/sparse/committor_test.py
msmtools/analysis/sparse/decomposition.py
msmtools/analysis/sparse/decomposition_test.py
msmtools/analysis/sparse/expectations.py
msmtools/analysis/sparse/expectations_test.py
msmtools/analysis/sparse/fingerprints.py
msmtools/analysis/sparse/fingerprints_test.py
msmtools/analysis/sparse/mean_first_passage_time.py
msmtools/analysis/sparse/mean_first_passage_time_test.py
msmtools/analysis/sparse/stationary_vector.py
msmtools/analysis/sparse/stationary_vector_test.py
msmtools/analysis/tests/P_rev_251x251.dat
msmtools/analysis/tests/__init__.py
msmtools/analysis/tests/test_assessment.py
